fastaudio/__init__.py
fastaudio/all.py
fastaudio/ci.py
fastaudio/util.py
fastaudio/augment/__init__.py
fastaudio/augment/all.py
fastaudio/augment/functional.py
fastaudio/augment/preprocess.py
fastaudio/augment/signal.py
fastaudio/augment/spectrogram.py
fastaudio/core/__init__.py
fastaudio/core/all.py
fastaudio/core/config.py
fastaudio/core/signal.py
fastaudio/core/spectrogram.py
fastaudio-1.0.2.dist-info/AUTHORS.rst
fastaudio-1.0.2.dist-info/LICENSE.txt
fastaudio-1.0.2.dist-info/METADATA
fastaudio-1.0.2.dist-info/WHEEL
fastaudio-1.0.2.dist-info/top_level.txt
fastaudio-1.0.2.dist-info/RECORD
