Metadata-Version: 2.1
Name: fastaudio
Version: 1.0.2
Summary: Audio Module for fastai version 2
Home-page: https://github.com/fastaudio/fastaudio
Author: scart97
Author-email: scart.lucas@gmail.com
License: mit
Project-URL: Documentation, https://fastaudio.github.io/
Platform: any
Classifier: Development Status :: 4 - Beta
Classifier: Programming Language :: Python
Requires-Dist: fastai (==2.3.1)
Requires-Dist: torchaudio (<0.9,>=0.7)
Requires-Dist: librosa (==0.8)
Requires-Dist: colorednoise (>=1.1)
Requires-Dist: IPython
Requires-Dist: fastcore (==1.3.20)
Provides-Extra: dev
Requires-Dist: mkdocs (>=1.1) ; extra == 'dev'
Requires-Dist: mkautodoc (>=0.1) ; extra == 'dev'
Requires-Dist: mkdocs-material (>=5.5) ; extra == 'dev'
Requires-Dist: mknotebooks (==0.6.1) ; extra == 'dev'
Requires-Dist: pre-commit (>=2.7) ; extra == 'dev'
Requires-Dist: recommonmark (>=0.6) ; extra == 'dev'
Requires-Dist: black (>=19.10b0) ; extra == 'dev'
Provides-Extra: testing
Requires-Dist: pytest (>=6.0) ; extra == 'testing'
Requires-Dist: pytest-cov (>=2.10) ; extra == 'testing'
Requires-Dist: papermill ; extra == 'testing'
Requires-Dist: jupyter ; extra == 'testing'
